MANIFEST.in
README.rst
setup.py
sketches/__init__.py
sketches/dist.py
sketches/fakeGPIO.py
sketches.egg-info/PKG-INFO
sketches.egg-info/SOURCES.txt
sketches.egg-info/dependency_links.txt
sketches.egg-info/entry_points.txt
sketches.egg-info/top_level.txt