Metadata-Version: 1.1
Name: sketches
Version: 1.0rc1
Summary: Write Arduino style sketches in Python
Home-page: https://github.com/IGBC/PySketch
Author: IGBC
Author-email: segfault@c-base.org
License: UNKNOWN
Platform: UNKNOWN
Classifier: Development Status :: 2 - Pre-Alpha
Classifier: Environment :: Console
Classifier: Intended Audience :: End Users/Desktop
Classifier: Intended Audience :: Developers
Classifier: Intended Audience :: Education
Classifier: License :: OSI Approved :: GNU General Public License v3 (GPLv3)
Classifier: Natural Language :: English
Classifier: Programming Language :: Python :: 3.4
Classifier: Programming Language :: Python :: 3 :: Only
Classifier: Topic :: Software Development :: Interpreters
Classifier: Topic :: Education
